zhmc_ansible_modules/__init__.py
zhmc_ansible_modules/zhmc_adapter.py
zhmc_ansible_modules/zhmc_cpc.py
zhmc_ansible_modules/zhmc_crypto_attachment.py
zhmc_ansible_modules/zhmc_hba.py
zhmc_ansible_modules/zhmc_nic.py
zhmc_ansible_modules/zhmc_partition.py
zhmc_ansible_modules/zhmc_storage_group.py
zhmc_ansible_modules/zhmc_storage_group_attachment.py
zhmc_ansible_modules/zhmc_storage_volume.py
zhmc_ansible_modules/zhmc_virtual_function.py
zhmc_ansible_modules/utils/__init__.py
zhmc_ansible_modules-0.8.4.dist-info/AUTHORS
zhmc_ansible_modules-0.8.4.dist-info/LICENSE
zhmc_ansible_modules-0.8.4.dist-info/METADATA
zhmc_ansible_modules-0.8.4.dist-info/WHEEL
zhmc_ansible_modules-0.8.4.dist-info/pbr.json
zhmc_ansible_modules-0.8.4.dist-info/top_level.txt
zhmc_ansible_modules-0.8.4.dist-info/RECORD
