Metadata-Version: 2.1
Name: zhmc-ansible-modules
Version: 0.8.4
Summary: Ansible modules managing a IBM Z via the HMC Web Services API.
Home-page: https://github.com/zhmcclient/zhmc-ansible-modules
Author: Andreas Scheuring, Juergen Leopold, Andreas Maier
Author-email: scheuran@de.ibm.com, leopoldj@de.ibm.com, maiera@de.ibm.com
Maintainer: Andreas Scheuring, Juergen Leopold, Andreas Maier
Maintainer-email: scheuran@de.ibm.com, leopoldj@de.ibm.com, maiera@de.ibm.com
License: Apache License, Version 2.0
Platform: UNKNOWN
Classifier: Development Status :: 5 - Production/Stable
Classifier: Intended Audience :: Developers
Classifier: Intended Audience :: Information Technology
Classifier: License :: OSI Approved :: Apache Software License
Classifier: Operating System :: OS Independent
Classifier: Programming Language :: Python
Classifier: Programming Language :: Python :: 2
Classifier: Programming Language :: Python :: 2.7
Classifier: Programming Language :: Python :: 3
Classifier: Programming Language :: Python :: 3.5
Classifier: Programming Language :: Python :: 3.6
Classifier: Programming Language :: Python :: 3.7
Classifier: Programming Language :: Python :: 3.8
Classifier: Programming Language :: Python :: 3.9
Requires-Python: >=2.7, !=3.0.*, !=3.1.*, !=3.2.*, !=3.3.*, !=3.4.*
Requires-Dist: ansible (>=2.4.0.0)
Requires-Dist: pbr (>=1.10.0)
Requires-Dist: requests (>=2.20.0)
Requires-Dist: certifi (>=2017.4.17)
Requires-Dist: zhmcclient (>=0.20.0)
Requires-Dist: packaging (>=20.0)
Requires-Dist: cryptography (<3.1,>=3.0) ; (python_version <= '3.5')
Requires-Dist: bcrypt (<3.2.0,>=3.0.0) ; (python_version <= '3.5')
Requires-Dist: PyYAML (>=5.1) ; (python_version == '2.7')
Requires-Dist: PyYAML (<5.3,>=5.1) ; (python_version == '3.4')
Requires-Dist: PyYAML (>=5.1) ; (python_version >= '3.5' and python_version <= '3.7')
Requires-Dist: cryptography (>=3.2) ; (python_version >= '3.6')
Requires-Dist: bcrypt (>=3.2.0) ; (python_version >= '3.6')
Requires-Dist: PyYAML (>=5.1.2) ; (python_version >= '3.8')
